ip/__init__.py
ip/core.py
myip_python-0.1.0.dist-info/LICENSE
myip_python-0.1.0.dist-info/METADATA
myip_python-0.1.0.dist-info/WHEEL
myip_python-0.1.0.dist-info/entry_points.txt
myip_python-0.1.0.dist-info/top_level.txt
myip_python-0.1.0.dist-info/RECORD
